greenops/__init__.py
greenops/advanced.py
greenops/api.py
greenops/context.py
greenops/datamodel.py
greenops/exceptions.py
greenops/functions.py
greenops/measure.py
greenops/torchmeasure.py
greenops-0.1.0.dist-info/LICENSE
greenops-0.1.0.dist-info/METADATA
greenops-0.1.0.dist-info/WHEEL
greenops-0.1.0.dist-info/top_level.txt
greenops-0.1.0.dist-info/RECORD
