Metadata-Version: 2.1
Name: greenops
Version: 0.1.0
Summary: Measuring the footprints of deep learning models at training, testing and evaluating to reduce energy consumption and carbon footprints
Home-page: https://github.com/hyperrixel/greenops
Author: Axel Ország-Krisz Dr., Richárd Ádám Vécsey Dr.
Author-email: greenops@hyperrixel.com
License: UNKNOWN
Project-URL: Bug Tracker, https://github.com/hyperrixel/greenops/issues
Platform: UNKNOWN
Classifier: Programming Language :: Python :: 3
Classifier: License :: OSI Approved :: MIT License
Classifier: Operating System :: OS Independent
Requires-Python: >=3.7
License-File: LICENSE
